[
  {
    "id": 2463,
    "name": "Aberdeen",
    "iso2": "ABE",
    "native": "Aberdeen",
    "latitude": "57.14971700",
    "longitude": "-2.09427800",
    "type": "council area",
    "timezone": "Europe/London",
    "CountryID": 232
  },
  {
    "id": 2401,
    "name": "Aberdeenshire",
    "iso2": "ABD",
    "native": "Aberdeenshire",
    "latitude": "57.16666700",
    "longitude": "-2.66666700",
    "type": "council area",
    "timezone": "Europe/London",
    "CountryID": 232
  },
  {
    "id": 2387,
    "name": "Angus",
    "iso2": "ANS",
    "native": "Angus",
    "latitude": "56.66666700",
    "longitude": "-2.91666700",
    "type": "council area",
    "timezone": "Europe/London",
    "CountryID": 232
  },
  {
    "id": 2412,
    "name": "Antrim and Newtownabbey",
    "iso2": "ANN",
    "native": "Antrim and Newtownabbey",
    "latitude": "54.68971360",
    "longitude": "-6.17106120",
    "type": "district",
    "timezone": "Europe/London",
    "CountryID": 232
  },
  {
    "id": 2523,
    "name": "Ards and North Down",
    "iso2": "AND",
    "native": "Ards and North Down",
    "latitude": "54.64896420",
    "longitude": "-5.56278520",
    "type": "district",
    "timezone": "Europe/London",
    "CountryID": 232
  },
  {
    "id": 2392,
    "name": "Argyll and Bute",
    "iso2": "AGB",
    "native": "Argyll and Bute",
    "latitude": "56.46034940",
    "longitude": "-5.86184190",
    "type": "council area",
    "timezone": "Europe/London",
    "CountryID": 232
  },
  {
    "id": 2324,
    "name": "Armagh, Banbridge and Craigavon",
    "iso2": "ABC",
    "native": "Armagh, Banbridge and Craigavon",
    "latitude": "54.31610850",
    "longitude": "-6.71891820",
    "type": "district",
    "timezone": "Europe/London",
    "CountryID": 232
  },
  {
    "id": 2356,
    "name": "Barking and Dagenham",
    "iso2": "BDG",
    "native": "Barking and Dagenham",
    "latitude": "51.55411710",
    "longitude": "0.15050510",
    "type": "london borough",
    "timezone": "Europe/London",
    "CountryID": 232
  },
  {
    "id": 2520,
    "name": "Barnet",
    "iso2": "BNE",
    "native": "Barnet",
    "latitude": "51.60496730",
    "longitude": "-0.20762950",
    "type": "london borough",
    "timezone": "Europe/London",
    "CountryID": 232
  },
  {
    "id": 2499,
    "name": "Barnsley",
    "iso2": "BNS",
    "native": "Barnsley",
    "latitude": "53.55277190",
    "longitude": "-1.48277550",
    "type": "metropolitan district",
    "timezone": "Europe/London",
    "CountryID": 232
  },
  {
    "id": 2339,
    "name": "Bath and North East Somerset",
    "iso2": "BAS",
    "native": "Bath and North East Somerset",
    "latitude": "51.35632380",
    "longitude": "-2.48666140",
    "type": "unitary authority",
    "timezone": "Europe/London",
    "CountryID": 232
  },
  {
    "id": 2507,
    "name": "Bedford",
    "iso2": "BDF",
    "native": "Bedford",
    "latitude": "52.18870140",
    "longitude": "-0.46658920",
    "type": "unitary authority",
    "timezone": "Europe/London",
    "CountryID": 232
  },
  {
    "id": 2311,
    "name": "Belfast",
    "iso2": "BFS",
    "native": "Belfast",
    "latitude": "54.59758040",
    "longitude": "-5.92770970",
    "type": "district",
    "timezone": "Europe/London",
    "CountryID": 232
  },
  {
    "id": 2307,
    "name": "Bexley",
    "iso2": "BEX",
    "native": "Bexley",
    "latitude": "51.44023750",
    "longitude": "0.14794940",
    "type": "london borough",
    "timezone": "Europe/London",
    "CountryID": 232
  },
  {
    "id": 2425,
    "name": "Birmingham",
    "iso2": "BIR",
    "native": "Birmingham",
    "latitude": "52.47969920",
    "longitude": "-1.90269110",
    "type": "metropolitan district",
    "timezone": "Europe/London",
    "CountryID": 232
  },
  {
    "id": 2329,
    "name": "Blackburn with Darwen",
    "iso2": "BBD",
    "native": "Blackburn with Darwen",
    "latitude": "53.69575220",
    "longitude": "-2.46829850",
    "type": "unitary authority",
    "timezone": "Europe/London",
    "CountryID": 232
  },
  {
    "id": 2451,
    "name": "Blackpool",
    "iso2": "BPL",
    "native": "Blackpool",
    "latitude": "53.81750530",
    "longitude": "-3.03567480",
    "type": "unitary authority",
    "timezone": "Europe/London",
    "CountryID": 232
  },
  {
    "id": 2530,
    "name": "Blaenau Gwent",
    "iso2": "BGW",
    "native": "Blaenau Gwent",
    "latitude": "51.75337110",
    "longitude": "-3.18484440",
    "type": "unitary authority",
    "timezone": "Europe/London",
    "CountryID": 232
  },
  {
    "id": 2504,
    "name": "Bolton",
    "iso2": "BOL",
    "native": "Bolton",
    "latitude": "55.92081780",
    "longitude": "-2.79059880",
    "type": "metropolitan district",
    "timezone": "Europe/London",
    "CountryID": 232
  },
  {
    "id": 5459,
    "name": "Bournemouth, Christchurch and Poole",
    "iso2": "BCP",
    "native": "Bournemouth, Christchurch and Poole",
    "latitude": "50.74570350",
    "longitude": "-2.19062240",
    "type": "unitary authority",
    "timezone": "Europe/London",
    "CountryID": 232
  },
  {
    "id": 2470,
    "name": "Bracknell Forest",
    "iso2": "BRC",
    "native": "Bracknell Forest",
    "latitude": "51.40026880",
    "longitude": "-0.74178880",
    "type": "unitary authority",
    "timezone": "Europe/London",
    "CountryID": 232
  },
  {
    "id": 2529,
    "name": "Bradford",
    "iso2": "BRD",
    "native": "Bradford",
    "latitude": "53.79598400",
    "longitude": "-1.75939800",
    "type": "metropolitan district",
    "timezone": "Europe/London",
    "CountryID": 232
  },
  {
    "id": 2291,
    "name": "Brent",
    "iso2": "BEN",
    "native": "Brent",
    "latitude": "52.01889180",
    "longitude": "-0.72350390",
    "type": "london borough",
    "timezone": "Europe/London",
    "CountryID": 232
  },
  {
    "id": 2452,
    "name": "Bridgend",
    "iso2": "BGE",
    "native": "Bridgend",
    "latitude": "51.50831990",
    "longitude": "-3.58120750",
    "type": "unitary authority",
    "timezone": "Europe/London",
    "CountryID": 232
  },
  {
    "id": 2395,
    "name": "Brighton and Hove",
    "iso2": "BNH",
    "native": "Brighton and Hove",
    "latitude": "50.84531690",
    "longitude": "-0.14974690",
    "type": "unitary authority",
    "timezone": "Europe/London",
    "CountryID": 232
  },
  {
    "id": 2413,
    "name": "Bristol",
    "iso2": "BST",
    "native": "Bristol",
    "latitude": "51.45380220",
    "longitude": "-2.59729850",
    "type": "unitary authority",
    "timezone": "Europe/London",
    "CountryID": 232
  },
  {
    "id": 2490,
    "name": "Bromley",
    "iso2": "BRY",
    "native": "Bromley",
    "latitude": "51.36797050",
    "longitude": "0.07006200",
    "type": "london borough",
    "timezone": "Europe/London",
    "CountryID": 232
  },
  {
    "id": 2405,
    "name": "Buckinghamshire",
    "iso2": "BKM",
    "native": "Buckinghamshire",
    "latitude": "51.78349940",
    "longitude": "-0.89464410",
    "type": "unitary authority",
    "timezone": "Europe/London",
    "CountryID": 232
  },
  {
    "id": 2459,
    "name": "Bury",
    "iso2": "BUR",
    "native": "Bury",
    "latitude": "53.59334980",
    "longitude": "-2.29660540",
    "type": "metropolitan district",
    "timezone": "Europe/London",
    "CountryID": 232
  },
  {
    "id": 2298,
    "name": "Caerphilly",
    "iso2": "CAY",
    "native": "Caerphilly",
    "latitude": "51.67238090",
    "longitude": "-3.17839380",
    "type": "unitary authority",
    "timezone": "Europe/London",
    "CountryID": 232
  },
  {
    "id": 2517,
    "name": "Calderdale",
    "iso2": "CLD",
    "native": "Calderdale",
    "latitude": "53.72047480",
    "longitude": "-1.96228860",
    "type": "metropolitan district",
    "timezone": "Europe/London",
    "CountryID": 232
  },
  {
    "id": 2423,
    "name": "Cambridgeshire",
    "iso2": "CAM",
    "native": "Cambridgeshire",
    "latitude": "52.33333300",
    "longitude": "0.08333300",
    "type": "two-tier county",
    "timezone": "Europe/London",
    "CountryID": 232
  },
  {
    "id": 2349,
    "name": "Camden",
    "iso2": "CMD",
    "native": "Camden",
    "latitude": "51.54547360",
    "longitude": "-0.16279020",
    "type": "london borough",
    "timezone": "Europe/London",
    "CountryID": 232
  },
  {
    "id": 2528,
    "name": "Cardiff",
    "iso2": "CRF",
    "native": "Cardiff",
    "latitude": "51.48158100",
    "longitude": "-3.17909000",
    "type": "unitary authority",
    "timezone": "Europe/London",
    "CountryID": 232
  },
  {
    "id": 2484,
    "name": "Carmarthenshire",
    "iso2": "CMN",
    "native": "Carmarthenshire",
    "latitude": "51.89366980",
    "longitude": "-4.21728270",
    "type": "unitary authority",
    "timezone": "Europe/London",
    "CountryID": 232
  },
  {
    "id": 2316,
    "name": "Causeway Coast and Glens",
    "iso2": "CCG",
    "native": "Causeway Coast and Glens",
    "latitude": "55.03612980",
    "longitude": "-6.59094490",
    "type": "district",
    "timezone": "Europe/London",
    "CountryID": 232
  },
  {
    "id": 2303,
    "name": "Central Bedfordshire",
    "iso2": "CBF",
    "native": "Central Bedfordshire",
    "latitude": "51.99803280",
    "longitude": "-0.47915140",
    "type": "unitary authority",
    "timezone": "Europe/London",
    "CountryID": 232
  },
  {
    "id": 2509,
    "name": "Ceredigion",
    "iso2": "CGN",
    "native": "Ceredigion",
    "latitude": "52.29457640",
    "longitude": "-3.95278100",
    "type": "unitary authority",
    "timezone": "Europe/London",
    "CountryID": 232
  },
  {
    "id": 2444,
    "name": "Cheshire East",
    "iso2": "CHE",
    "native": "Cheshire East",
    "latitude": "53.16734220",
    "longitude": "-2.29288030",
    "type": "unitary authority",
    "timezone": "Europe/London",
    "CountryID": 232
  },
  {
    "id": 2442,
    "name": "Cheshire West and Chester",
    "iso2": "CHW",
    "native": "Cheshire West and Chester",
    "latitude": "53.16379790",
    "longitude": "-2.72853610",
    "type": "unitary authority",
    "timezone": "Europe/London",
    "CountryID": 232
  },
  {
    "id": 2475,
    "name": "City of Kingston upon Hull",
    "iso2": "KHL",
    "native": "City of Kingston upon Hull",
    "latitude": "53.76762360",
    "longitude": "-0.32741980",
    "type": "unitary authority",
    "timezone": "Europe/London",
    "CountryID": 232
  },
  {
    "id": 2294,
    "name": "City of Southampton",
    "iso2": "STH",
    "native": "City of Southampton",
    "latitude": "50.90018780",
    "longitude": "-1.41395570",
    "type": "unitary authority",
    "timezone": "Europe/London",
    "CountryID": 232
  },
  {
    "id": 2450,
    "name": "Clackmannanshire",
    "iso2": "CLK",
    "native": "Clackmannanshire",
    "latitude": "56.16639500",
    "longitude": "-3.75139680",
    "type": "council area",
    "timezone": "Europe/London",
    "CountryID": 232
  },
  {
    "id": 2352,
    "name": "Conwy",
    "iso2": "CWY",
    "native": "Conwy",
    "latitude": "53.28118220",
    "longitude": "-3.82870120",
    "type": "unitary authority",
    "timezone": "Europe/London",
    "CountryID": 232
  },
  {
    "id": 2312,
    "name": "Cornwall",
    "iso2": "CON",
    "native": "Cornwall",
    "latitude": "50.44334890",
    "longitude": "-4.62465660",
    "type": "unitary authority",
    "timezone": "Europe/London",
    "CountryID": 232
  },
  {
    "id": 2438,
    "name": "Coventry",
    "iso2": "COV",
    "native": "Coventry",
    "latitude": "52.40682200",
    "longitude": "-1.51969300",
    "type": "metropolitan district",
    "timezone": "Europe/London",
    "CountryID": 232
  },
  {
    "id": 2512,
    "name": "Croydon",
    "iso2": "CRY",
    "native": "Croydon",
    "latitude": "51.37130490",
    "longitude": "-0.10195700",
    "type": "london borough",
    "timezone": "Europe/London",
    "CountryID": 232
  },
  {
    "id": 2334,
    "name": "Cumbria",
    "iso2": "CMA",
    "native": "Cumbria",
    "latitude": "54.61431360",
    "longitude": "-2.94208990",
    "type": "two-tier county",
    "timezone": "Europe/London",
    "CountryID": 232
  },
  {
    "id": 2389,
    "name": "Darlington",
    "iso2": "DAL",
    "native": "Darlington",
    "latitude": "54.53525640",
    "longitude": "-1.55294300",
    "type": "unitary authority",
    "timezone": "Europe/London",
    "CountryID": 232
  },
  {
    "id": 2497,
    "name": "Denbighshire",
    "iso2": "DEN",
    "native": "Denbighshire",
    "latitude": "53.10978950",
    "longitude": "-3.36712840",
    "type": "unitary authority",
    "timezone": "Europe/London",
    "CountryID": 232
  },
  {
    "id": 2485,
    "name": "Derby",
    "iso2": "DER",
    "native": "Derby",
    "latitude": "53.16669270",
    "longitude": "-1.58332230",
    "type": "unitary authority",
    "timezone": "Europe/London",
    "CountryID": 232
  },
  {
    "id": 2403,
    "name": "Derbyshire",
    "iso2": "DBY",
    "native": "Derbyshire",
    "latitude": "53.11850330",
    "longitude": "-1.55661790",
    "type": "two-tier county",
    "timezone": "Europe/London",
    "CountryID": 232
  },
  {
    "id": 2446,
    "name": "Derry City and Strabane",
    "iso2": "DRS",
    "native": "Derry City and Strabane",
    "latitude": "55.00474430",
    "longitude": "-7.32092220",
    "type": "district",
    "timezone": "Europe/London",
    "CountryID": 232
  },
  {
    "id": 2491,
    "name": "Devon",
    "iso2": "DEV",
    "native": "Devon",
    "latitude": "50.72414050",
    "longitude": "-3.66077880",
    "type": "two-tier county",
    "timezone": "Europe/London",
    "CountryID": 232
  },
  {
    "id": 2364,
    "name": "Doncaster",
    "iso2": "DNC",
    "native": "Doncaster",
    "latitude": "53.52282000",
    "longitude": "-1.12846200",
    "type": "metropolitan district",
    "timezone": "Europe/London",
    "CountryID": 232
  },
  {
    "id": 2345,
    "name": "Dorset",
    "iso2": "DOR",
    "native": "Dorset",
    "latitude": "50.74876350",
    "longitude": "-2.34447860",
    "type": "two-tier county",
    "timezone": "Europe/London",
    "CountryID": 232
  },
  {
    "id": 2457,
    "name": "Dudley",
    "iso2": "DUD",
    "native": "Dudley",
    "latitude": "55.05412430",
    "longitude": "-1.59498640",
    "type": "metropolitan district",
    "timezone": "Europe/London",
    "CountryID": 232
  },
  {
    "id": 2415,
    "name": "Dumfries and Galloway",
    "iso2": "DGY",
    "native": "Dumfries and Galloway",
    "latitude": "55.08333300",
    "longitude": "-3.83333300",
    "type": "council area",
    "timezone": "Europe/London",
    "CountryID": 232
  },
  {
    "id": 2511,
    "name": "Dundee",
    "iso2": "DND",
    "native": "Dundee",
    "latitude": "56.46201800",
    "longitude": "-2.97072100",
    "type": "council area",
    "timezone": "Europe/London",
    "CountryID": 232
  },
  {
    "id": 2406,
    "name": "Durham",
    "iso2": "DUR",
    "native": "Durham",
    "latitude": "54.66666700",
    "longitude": "-1.75000000",
    "type": "unitary authority",
    "timezone": "Europe/London",
    "CountryID": 232
  },
  {
    "id": 2532,
    "name": "Ealing",
    "iso2": "EAL",
    "native": "Ealing",
    "latitude": "51.52508460",
    "longitude": "-0.31429350",
    "type": "london borough",
    "timezone": "Europe/London",
    "CountryID": 232
  },
  {
    "id": 2374,
    "name": "East Ayrshire",
    "iso2": "EAY",
    "native": "East Ayrshire",
    "latitude": "55.50000000",
    "longitude": "-4.25000000",
    "type": "council area",
    "timezone": "Europe/London",
    "CountryID": 232
  },
  {
    "id": 2454,
    "name": "East Dunbartonshire",
    "iso2": "EDU",
    "native": "East Dunbartonshire",
    "latitude": "55.93333300",
    "longitude": "-4.20000000",
    "type": "council area",
    "timezone": "Europe/London",
    "CountryID": 232
  },
  {
    "id": 2462,
    "name": "East Lothian",
    "iso2": "ELN",
    "native": "East Lothian",
    "latitude": "55.91579700",
    "longitude": "-2.75119520",
    "type": "council area",
    "timezone": "Europe/London",
    "CountryID": 232
  },
  {
    "id": 2333,
    "name": "East Renfrewshire",
    "iso2": "ERW",
    "native": "East Renfrewshire",
    "latitude": "55.74947930",
    "longitude": "-4.36065920",
    "type": "council area",
    "timezone": "Europe/London",
    "CountryID": 232
  },
  {
    "id": 2370,
    "name": "East Riding of Yorkshire",
    "iso2": "ERY",
    "native": "East Riding of Yorkshire",
    "latitude": "53.87359650",
    "longitude": "-0.53477880",
    "type": "unitary authority",
    "timezone": "Europe/London",
    "CountryID": 232
  },
  {
    "id": 2414,
    "name": "East Sussex",
    "iso2": "ESX",
    "native": "East Sussex",
    "latitude": "50.94042660",
    "longitude": "0.36999780",
    "type": "two-tier county",
    "timezone": "Europe/London",
    "CountryID": 232
  },
  {
    "id": 2428,
    "name": "Edinburgh",
    "iso2": "EDH",
    "native": "Edinburgh",
    "latitude": "55.95325200",
    "longitude": "-3.18826700",
    "type": "council area",
    "timezone": "Europe/London",
    "CountryID": 232
  },
  {
    "id": 2476,
    "name": "Enfield",
    "iso2": "ENF",
    "native": "Enfield",
    "latitude": "51.65263840",
    "longitude": "-0.09086390",
    "type": "london borough",
    "timezone": "Europe/London",
    "CountryID": 232
  },
  {
    "id": 2336,
    "name": "England",
    "iso2": "ENG",
    "native": "England",
    "latitude": "52.53102140",
    "longitude": "-1.26490620",
    "type": "country",
    "timezone": "Europe/London",
    "CountryID": 232
  },
  {
    "id": 2410,
    "name": "Essex",
    "iso2": "ESS",
    "native": "Essex",
    "latitude": "51.77046790",
    "longitude": "0.46466980",
    "type": "two-tier county",
    "timezone": "Europe/London",
    "CountryID": 232
  },
  {
    "id": 2344,
    "name": "Falkirk",
    "iso2": "FAL",
    "native": "Falkirk",
    "latitude": "56.00187750",
    "longitude": "-3.78391310",
    "type": "council area",
    "timezone": "Europe/London",
    "CountryID": 232
  },
  {
    "id": 2366,
    "name": "Fermanagh and Omagh",
    "iso2": "FMO",
    "native": "Fermanagh and Omagh",
    "latitude": "54.35588630",
    "longitude": "-7.59366360",
    "type": "district",
    "timezone": "Europe/London",
    "CountryID": 232
  },
  {
    "id": 2479,
    "name": "Fife",
    "iso2": "FIF",
    "native": "Fife",
    "latitude": "56.33333310",
    "longitude": "-3.00000010",
    "type": "council area",
    "timezone": "Europe/London",
    "CountryID": 232
  },
  {
    "id": 2437,
    "name": "Flintshire",
    "iso2": "FLN",
    "native": "Flintshire",
    "latitude": "53.21650960",
    "longitude": "-3.14021890",
    "type": "unitary authority",
    "timezone": "Europe/London",
    "CountryID": 232
  },
  {
    "id": 2431,
    "name": "Gateshead",
    "iso2": "GAT",
    "native": "Gateshead",
    "latitude": "54.96257890",
    "longitude": "-1.60192940",
    "type": "metropolitan district",
    "timezone": "Europe/London",
    "CountryID": 232
  },
  {
    "id": 2404,
    "name": "Glasgow",
    "iso2": "GLG",
    "native": "Glasgow",
    "latitude": "55.86423700",
    "longitude": "-4.25180600",
    "type": "council area",
    "timezone": "Europe/London",
    "CountryID": 232
  },
  {
    "id": 2373,
    "name": "Gloucestershire",
    "iso2": "GLS",
    "native": "Gloucestershire",
    "latitude": "51.83333130",
    "longitude": "-2.16666740",
    "type": "two-tier county",
    "timezone": "Europe/London",
    "CountryID": 232
  },
  {
    "id": 2492,
    "name": "Greenwich",
    "iso2": "GRE",
    "native": "Greenwich",
    "latitude": "51.46862560",
    "longitude": "0.04883060",
    "type": "london borough",
    "timezone": "Europe/London",
    "CountryID": 232
  },
  {
    "id": 2379,
    "name": "Gwynedd",
    "iso2": "GWN",
    "native": "Gwynedd",
    "latitude": "52.90895850",
    "longitude": "-3.83352440",
    "type": "unitary authority",
    "timezone": "Europe/London",
    "CountryID": 232
  },
  {
    "id": 2411,
    "name": "Hackney",
    "iso2": "HCK",
    "native": "Hackney",
    "latitude": "51.54888190",
    "longitude": "-0.04766910",
    "type": "london borough",
    "timezone": "Europe/London",
    "CountryID": 232
  },
  {
    "id": 2466,
    "name": "Halton",
    "iso2": "HAL",
    "native": "Stop",
    "latitude": "55.00490990",
    "longitude": "-2.00452160",
    "type": "unitary authority",
    "timezone": "Europe/London",
    "CountryID": 232
  },
  {
    "id": 2448,
    "name": "Hammersmith and Fulham",
    "iso2": "HMF",
    "native": "Hammersmith and Fulham",
    "latitude": "51.49901560",
    "longitude": "-0.22915000",
    "type": "london borough",
    "timezone": "Europe/London",
    "CountryID": 232
  },
  {
    "id": 2435,
    "name": "Hampshire",
    "iso2": "HAM",
    "native": "Hampshire",
    "latitude": "51.04498140",
    "longitude": "-1.24331330",
    "type": "two-tier county",
    "timezone": "Europe/London",
    "CountryID": 232
  },
  {
    "id": 2306,
    "name": "Haringey",
    "iso2": "HRY",
    "native": "Haringey",
    "latitude": "51.59061130",
    "longitude": "-0.11097090",
    "type": "london borough",
    "timezone": "Europe/London",
    "CountryID": 232
  },
  {
    "id": 2385,
    "name": "Harrow",
    "iso2": "HRW",
    "native": "Harrow",
    "latitude": "51.58816270",
    "longitude": "-0.34228510",
    "type": "london borough",
    "timezone": "Europe/London",
    "CountryID": 232
  },
  {
    "id": 2309,
    "name": "Hartlepool",
    "iso2": "HPL",
    "native": "Hartlepool",
    "latitude": "54.69174500",
    "longitude": "-1.21292600",
    "type": "unitary authority",
    "timezone": "Europe/London",
    "CountryID": 232
  },
  {
    "id": 2347,
    "name": "Havering",
    "iso2": "HAV",
    "native": "Gardening",
    "latitude": "51.55792620",
    "longitude": "0.24981280",
    "type": "london borough",
    "timezone": "Europe/London",
    "CountryID": 232
  },
  {
    "id": 2500,
    "name": "Herefordshire",
    "iso2": "HEF",
    "native": "Herefordshire",
    "latitude": "52.08333300",
    "longitude": "-2.75000000",
    "type": "unitary authority",
    "timezone": "Europe/London",
    "CountryID": 232
  },
  {
    "id": 2369,
    "name": "Hertfordshire",
    "iso2": "HRT",
    "native": "Hertfordshire",
    "latitude": "51.84005230",
    "longitude": "-0.09785520",
    "type": "two-tier county",
    "timezone": "Europe/London",
    "CountryID": 232
  },
  {
    "id": 2383,
    "name": "Highland",
    "iso2": "HLD",
    "native": "Highland",
    "latitude": "57.50663570",
    "longitude": "-5.00383670",
    "type": "council area",
    "timezone": "Europe/London",
    "CountryID": 232
  },
  {
    "id": 2376,
    "name": "Hillingdon",
    "iso2": "HIL",
    "native": "Hillingdon",
    "latitude": "51.53518320",
    "longitude": "-0.44813780",
    "type": "london borough",
    "timezone": "Europe/London",
    "CountryID": 232
  },
  {
    "id": 2380,
    "name": "Hounslow",
    "iso2": "HNS",
    "native": "Hounslow",
    "latitude": "51.46173340",
    "longitude": "-0.38013100",
    "type": "london borough",
    "timezone": "Europe/London",
    "CountryID": 232
  },
  {
    "id": 2388,
    "name": "Inverclyde",
    "iso2": "IVC",
    "native": "Inverclyde",
    "latitude": "55.90000000",
    "longitude": "-4.75000000",
    "type": "council area",
    "timezone": "Europe/London",
    "CountryID": 232
  },
  {
    "id": 5458,
    "name": "Isle of Anglesey",
    "iso2": "AGY",
    "native": "Isle of Anglesey",
    "latitude": "53.28070200",
    "longitude": "-4.68995190",
    "type": "unitary authority",
    "timezone": "Europe/London",
    "CountryID": 232
  },
  {
    "id": 2289,
    "name": "Isle of Wight",
    "iso2": "IOW",
    "native": "Isle of Wight",
    "latitude": "50.67104820",
    "longitude": "-1.33271110",
    "type": "unitary authority",
    "timezone": "Europe/London",
    "CountryID": 232
  },
  {
    "id": 2343,
    "name": "Isles of Scilly",
    "iso2": "IOS",
    "native": "Isles of Scilly",
    "latitude": "49.92034090",
    "longitude": "-6.29287910",
    "type": "unitary authority",
    "timezone": "Europe/London",
    "CountryID": 232
  },
  {
    "id": 2319,
    "name": "Islington",
    "iso2": "ISL",
    "native": "Islington",
    "latitude": "51.54650630",
    "longitude": "-0.10580580",
    "type": "london borough",
    "timezone": "Europe/London",
    "CountryID": 232
  },
  {
    "id": 2368,
    "name": "Kensington and Chelsea",
    "iso2": "KEC",
    "native": "Kensington and Chelsea",
    "latitude": "51.49908050",
    "longitude": "-0.19382530",
    "type": "london borough",
    "timezone": "Europe/London",
    "CountryID": 232
  },
  {
    "id": 2464,
    "name": "Kent",
    "iso2": "KEN",
    "native": "Kent",
    "latitude": "51.20707480",
    "longitude": "0.72103620",
    "type": "two-tier county",
    "timezone": "Europe/London",
    "CountryID": 232
  },
  {
    "id": 2481,
    "name": "Kingston upon Thames",
    "iso2": "KTT",
    "native": "Kingston upon Thames",
    "latitude": "51.38177630",
    "longitude": "-0.27699330",
    "type": "london borough",
    "timezone": "Europe/London",
    "CountryID": 232
  },
  {
    "id": 2371,
    "name": "Kirklees",
    "iso2": "KIR",
    "native": "Kirklees",
    "latitude": "53.64226350",
    "longitude": "-1.78094330",
    "type": "metropolitan district",
    "timezone": "Europe/London",
    "CountryID": 232
  },
  {
    "id": 2330,
    "name": "Knowsley",
    "iso2": "KWL",
    "native": "Knowsley",
    "latitude": "53.45459400",
    "longitude": "-2.85290700",
    "type": "metropolitan district",
    "timezone": "Europe/London",
    "CountryID": 232
  },
  {
    "id": 2396,
    "name": "Lambeth",
    "iso2": "LBH",
    "native": "Lambeth",
    "latitude": "51.49521110",
    "longitude": "-0.11633540",
    "type": "london borough",
    "timezone": "Europe/London",
    "CountryID": 232
  },
  {
    "id": 2495,
    "name": "Lancashire",
    "iso2": "LAN",
    "native": "Lancashire",
    "latitude": "53.86117120",
    "longitude": "-2.56509450",
    "type": "two-tier county",
    "timezone": "Europe/London",
    "CountryID": 232
  },
  {
    "id": 2503,
    "name": "Leeds",
    "iso2": "LDS",
    "native": "Leeds",
    "latitude": "53.80075540",
    "longitude": "-1.54907740",
    "type": "metropolitan district",
    "timezone": "Europe/London",
    "CountryID": 232
  },
  {
    "id": 2318,
    "name": "Leicester",
    "iso2": "LCE",
    "native": "Leicester",
    "latitude": "52.63687780",
    "longitude": "-1.13975920",
    "type": "unitary authority",
    "timezone": "Europe/London",
    "CountryID": 232
  },
  {
    "id": 2516,
    "name": "Leicestershire",
    "iso2": "LEC",
    "native": "Leicestershire",
    "latitude": "52.68491370",
    "longitude": "-1.18476530",
    "type": "two-tier county",
    "timezone": "Europe/London",
    "CountryID": 232
  },
  {
    "id": 2358,
    "name": "Lewisham",
    "iso2": "LEW",
    "native": "Lewisham",
    "latitude": "51.45352070",
    "longitude": "-0.01247510",
    "type": "london borough",
    "timezone": "Europe/London",
    "CountryID": 232
  },
  {
    "id": 2355,
    "name": "Lincolnshire",
    "iso2": "LIN",
    "native": "Lincolnshire",
    "latitude": "53.12822670",
    "longitude": "-0.19019740",
    "type": "two-tier county",
    "timezone": "Europe/London",
    "CountryID": 232
  },
  {
    "id": 2460,
    "name": "Lisburn and Castlereagh",
    "iso2": "LBC",
    "native": "Lisburn and Castlereagh",
    "latitude": "54.49740260",
    "longitude": "-6.03307390",
    "type": "district",
    "timezone": "Europe/London",
    "CountryID": 232
  },
  {
    "id": 2340,
    "name": "Liverpool",
    "iso2": "LIV",
    "native": "Liverpool",
    "latitude": "53.40719910",
    "longitude": "-2.99168000",
    "type": "metropolitan district",
    "timezone": "Europe/London",
    "CountryID": 232
  },
  {
    "id": 2424,
    "name": "London",
    "iso2": "LND",
    "native": "London",
    "latitude": "51.51234430",
    "longitude": "-0.09098520",
    "type": "city",
    "timezone": "Europe/London",
    "CountryID": 232
  },
  {
    "id": 5460,
    "name": "Luton",
    "iso2": "LUT",
    "native": "Luton",
    "latitude": "51.89107730",
    "longitude": "-0.51033490",
    "type": "unitary authority",
    "timezone": "Europe/London",
    "CountryID": 232
  },
  {
    "id": 2398,
    "name": "Manchester",
    "iso2": "MAN",
    "native": "Manchester",
    "latitude": "53.48075930",
    "longitude": "-2.24263050",
    "type": "metropolitan district",
    "timezone": "Europe/London",
    "CountryID": 232
  },
  {
    "id": 2381,
    "name": "Medway",
    "iso2": "MDW",
    "native": "Medway",
    "latitude": "51.41573860",
    "longitude": "0.56873090",
    "type": "unitary authority",
    "timezone": "Europe/London",
    "CountryID": 232
  },
  {
    "id": 2328,
    "name": "Merthyr Tydfil",
    "iso2": "MTY",
    "native": "Merthyr Tydfil",
    "latitude": "51.74674740",
    "longitude": "-3.38132750",
    "type": "unitary authority",
    "timezone": "Europe/London",
    "CountryID": 232
  },
  {
    "id": 2483,
    "name": "Merton",
    "iso2": "MRT",
    "native": "Merton",
    "latitude": "51.41086980",
    "longitude": "-0.18809710",
    "type": "london borough",
    "timezone": "Europe/London",
    "CountryID": 232
  },
  {
    "id": 2429,
    "name": "Mid and East Antrim",
    "iso2": "MEA",
    "native": "Mid and East Antrim",
    "latitude": "54.87257450",
    "longitude": "-6.15024600",
    "type": "district",
    "timezone": "Europe/London",
    "CountryID": 232
  },
  {
    "id": 2399,
    "name": "Mid Ulster",
    "iso2": "MUL",
    "native": "Mid Ulster",
    "latitude": "54.63855730",
    "longitude": "-6.69258100",
    "type": "district",
    "timezone": "Europe/London",
    "CountryID": 232
  },
  {
    "id": 2332,
    "name": "Middlesbrough",
    "iso2": "MDB",
    "native": "Middlesbrough",
    "latitude": "54.57422700",
    "longitude": "-1.23495600",
    "type": "unitary authority",
    "timezone": "Europe/London",
    "CountryID": 232
  },
  {
    "id": 2519,
    "name": "Midlothian",
    "iso2": "MLN",
    "native": "Midlothian",
    "latitude": "55.83333300",
    "longitude": "-3.08333300",
    "type": "council area",
    "timezone": "Europe/London",
    "CountryID": 232
  },
  {
    "id": 2416,
    "name": "Milton Keynes",
    "iso2": "MIK",
    "native": "Milton Keynes",
    "latitude": "52.04065020",
    "longitude": "-0.75940920",
    "type": "unitary authority",
    "timezone": "Europe/London",
    "CountryID": 232
  },
  {
    "id": 2402,
    "name": "Monmouthshire",
    "iso2": "MON",
    "native": "Monmouthshire",
    "latitude": "51.75010580",
    "longitude": "-2.83333310",
    "type": "unitary authority",
    "timezone": "Europe/London",
    "CountryID": 232
  },
  {
    "id": 2360,
    "name": "Moray",
    "iso2": "MRY",
    "native": "Moray",
    "latitude": "57.41666700",
    "longitude": "-3.25000000",
    "type": "council area",
    "timezone": "Europe/London",
    "CountryID": 232
  },
  {
    "id": 2351,
    "name": "Neath Port Talbot",
    "iso2": "NTL",
    "native": "Neath Port Talbot",
    "latitude": "51.66895570",
    "longitude": "-3.72181790",
    "type": "unitary authority",
    "timezone": "Europe/London",
    "CountryID": 232
  },
  {
    "id": 2458,
    "name": "Newcastle upon Tyne",
    "iso2": "NET",
    "native": "Newcastle upon Tyne",
    "latitude": "54.97825200",
    "longitude": "-1.61778000",
    "type": "metropolitan district",
    "timezone": "Europe/London",
    "CountryID": 232
  },
  {
    "id": 2418,
    "name": "Newham",
    "iso2": "NWM",
    "native": "Newham",
    "latitude": "51.52551620",
    "longitude": "0.03521630",
    "type": "london borough",
    "timezone": "Europe/London",
    "CountryID": 232
  },
  {
    "id": 2524,
    "name": "Newport",
    "iso2": "NWP",
    "native": "Newport",
    "latitude": "52.76885940",
    "longitude": "-2.37836760",
    "type": "unitary authority",
    "timezone": "Europe/London",
    "CountryID": 232
  },
  {
    "id": 2534,
    "name": "Newry, Mourne and Down",
    "iso2": "NMD",
    "native": "Newry, Mourne and Down",
    "latitude": "54.17752830",
    "longitude": "-6.33750600",
    "type": "district",
    "timezone": "Europe/London",
    "CountryID": 232
  },
  {
    "id": 2473,
    "name": "Norfolk",
    "iso2": "NFK",
    "native": "Norfolk",
    "latitude": "52.66666700",
    "longitude": "1.00000000",
    "type": "two-tier county",
    "timezone": "Europe/London",
    "CountryID": 232
  },
  {
    "id": 2535,
    "name": "North Ayrshire",
    "iso2": "NAY",
    "native": "North Ayrshire",
    "latitude": "55.72785080",
    "longitude": "-4.72717670",
    "type": "council area",
    "timezone": "Europe/London",
    "CountryID": 232
  },
  {
    "id": 2384,
    "name": "North East Lincolnshire",
    "iso2": "NEL",
    "native": "North East Lincolnshire",
    "latitude": "53.53680330",
    "longitude": "-0.09368100",
    "type": "unitary authority",
    "timezone": "Europe/London",
    "CountryID": 232
  },
  {
    "id": 2487,
    "name": "North Lanarkshire",
    "iso2": "NLK",
    "native": "North Lanarkshire",
    "latitude": "55.88305070",
    "longitude": "-3.94615510",
    "type": "council area",
    "timezone": "Europe/London",
    "CountryID": 232
  },
  {
    "id": 2453,
    "name": "North Lincolnshire",
    "iso2": "NLN",
    "native": "North Lincolnshire",
    "latitude": "53.58974410",
    "longitude": "-0.60232300",
    "type": "unitary authority",
    "timezone": "Europe/London",
    "CountryID": 232
  },
  {
    "id": 5461,
    "name": "North Northamptonshire",
    "iso2": "NNH",
    "native": "North Northamptonshire",
    "latitude": "52.41710850",
    "longitude": "-0.95355110",
    "type": "unitary authority",
    "timezone": "Europe/London",
    "CountryID": 232
  },
  {
    "id": 2430,
    "name": "North Somerset",
    "iso2": "NSM",
    "native": "North Somerset",
    "latitude": "51.39663050",
    "longitude": "-2.76912890",
    "type": "unitary authority",
    "timezone": "Europe/London",
    "CountryID": 232
  },
  {
    "id": 2521,
    "name": "North Tyneside",
    "iso2": "NTY",
    "native": "North Tyneside",
    "latitude": "55.02979940",
    "longitude": "-1.50825600",
    "type": "metropolitan district",
    "timezone": "Europe/London",
    "CountryID": 232
  },
  {
    "id": 2522,
    "name": "North Yorkshire",
    "iso2": "NYK",
    "native": "North Yorkshire",
    "latitude": "54.09159280",
    "longitude": "-1.53591130",
    "type": "two-tier county",
    "timezone": "Europe/London",
    "CountryID": 232
  },
  {
    "id": 2337,
    "name": "Northern Ireland",
    "iso2": "NIR",
    "native": "Northern Ireland",
    "latitude": "54.58598360",
    "longitude": "-6.95915540",
    "type": "province",
    "timezone": "Europe/London",
    "CountryID": 232
  },
  {
    "id": 2365,
    "name": "Northumberland",
    "iso2": "NBL",
    "native": "Northumberland",
    "latitude": "55.25000000",
    "longitude": "-2.00055900",
    "type": "unitary authority",
    "timezone": "Europe/London",
    "CountryID": 232
  },
  {
    "id": 2359,
    "name": "Nottingham",
    "iso2": "NGM",
    "native": "Nottingham",
    "latitude": "52.95478320",
    "longitude": "-1.15810860",
    "type": "unitary authority",
    "timezone": "Europe/London",
    "CountryID": 232
  },
  {
    "id": 2456,
    "name": "Nottinghamshire",
    "iso2": "NTT",
    "native": "Nottinghamshire",
    "latitude": "53.14592880",
    "longitude": "-1.02149710",
    "type": "two-tier county",
    "timezone": "Europe/London",
    "CountryID": 232
  },
  {
    "id": 2477,
    "name": "Oldham",
    "iso2": "OLD",
    "native": "Oldham",
    "latitude": "53.54157970",
    "longitude": "-2.11478310",
    "type": "metropolitan district",
    "timezone": "Europe/London",
    "CountryID": 232
  },
  {
    "id": 2474,
    "name": "Orkney Islands",
    "iso2": "ORK",
    "native": "Orkney Islands",
    "latitude": "58.94182310",
    "longitude": "-3.12969440",
    "type": "council area",
    "timezone": "Europe/London",
    "CountryID": 232
  },
  {
    "id": 2353,
    "name": "Outer Hebrides",
    "iso2": "ELS",
    "native": "Outer Hebrides",
    "latitude": "57.66666700",
    "longitude": "-7.16666700",
    "type": "council area",
    "timezone": "Europe/London",
    "CountryID": 232
  },
  {
    "id": 2321,
    "name": "Oxfordshire",
    "iso2": "OXF",
    "native": "Oxfordshire",
    "latitude": "51.83333300",
    "longitude": "-1.25000000",
    "type": "two-tier county",
    "timezone": "Europe/London",
    "CountryID": 232
  },
  {
    "id": 2486,
    "name": "Pembrokeshire",
    "iso2": "PEM",
    "native": "Pembrokeshire",
    "latitude": "51.83392090",
    "longitude": "-4.91666700",
    "type": "unitary authority",
    "timezone": "Europe/London",
    "CountryID": 232
  },
  {
    "id": 2325,
    "name": "Perth and Kinross",
    "iso2": "PKN",
    "native": "Perth and Kinross",
    "latitude": "56.50000000",
    "longitude": "-3.75000000",
    "type": "council area",
    "timezone": "Europe/London",
    "CountryID": 232
  },
  {
    "id": 2297,
    "name": "Peterborough",
    "iso2": "PTE",
    "native": "Peterborough",
    "latitude": "52.57257690",
    "longitude": "-0.24273360",
    "type": "unitary authority",
    "timezone": "Europe/London",
    "CountryID": 232
  },
  {
    "id": 2514,
    "name": "Plymouth",
    "iso2": "PLY",
    "native": "Plymouth",
    "latitude": "50.37141220",
    "longitude": "-4.14244510",
    "type": "unitary authority",
    "timezone": "Europe/London",
    "CountryID": 232
  },
  {
    "id": 2305,
    "name": "Portsmouth",
    "iso2": "POR",
    "native": "Portsmouth",
    "latitude": "50.80003100",
    "longitude": "-1.09060230",
    "type": "unitary authority",
    "timezone": "Europe/London",
    "CountryID": 232
  },
  {
    "id": 2441,
    "name": "Powys",
    "iso2": "POW",
    "native": "Powys",
    "latitude": "52.32714990",
    "longitude": "-3.35533520",
    "type": "unitary authority",
    "timezone": "Europe/London",
    "CountryID": 232
  },
  {
    "id": 2455,
    "name": "Reading",
    "iso2": "RDG",
    "native": "Reading",
    "latitude": "51.45149530",
    "longitude": "-0.98363420",
    "type": "unitary authority",
    "timezone": "Europe/London",
    "CountryID": 232
  },
  {
    "id": 2397,
    "name": "Redbridge",
    "iso2": "RDB",
    "native": "Redbridge",
    "latitude": "51.57658280",
    "longitude": "0.04534010",
    "type": "london borough",
    "timezone": "Europe/London",
    "CountryID": 232
  },
  {
    "id": 2527,
    "name": "Redcar and Cleveland",
    "iso2": "RCC",
    "native": "Redcar and Cleveland",
    "latitude": "54.56790560",
    "longitude": "-1.00549630",
    "type": "unitary authority",
    "timezone": "Europe/London",
    "CountryID": 232
  },
  {
    "id": 2443,
    "name": "Renfrewshire",
    "iso2": "RFW",
    "native": "Renfrewshire",
    "latitude": "55.83333300",
    "longitude": "-4.50000000",
    "type": "council area",
    "timezone": "Europe/London",
    "CountryID": 232
  },
  {
    "id": 2301,
    "name": "Rhondda Cynon Taf",
    "iso2": "RCT",
    "native": "Rhondda Cynon Taf",
    "latitude": "51.66516360",
    "longitude": "-3.45775580",
    "type": "unitary authority",
    "timezone": "Europe/London",
    "CountryID": 232
  },
  {
    "id": 2501,
    "name": "Richmond upon Thames",
    "iso2": "RIC",
    "native": "Richmond upon Thames",
    "latitude": "51.44055290",
    "longitude": "-0.30763940",
    "type": "london borough",
    "timezone": "Europe/London",
    "CountryID": 232
  },
  {
    "id": 2327,
    "name": "Rochdale",
    "iso2": "RCH",
    "native": "Roughly",
    "latitude": "53.60971360",
    "longitude": "-2.15610000",
    "type": "metropolitan district",
    "timezone": "Europe/London",
    "CountryID": 232
  },
  {
    "id": 2308,
    "name": "Rotherham",
    "iso2": "ROT",
    "native": "Rotherham",
    "latitude": "53.43260350",
    "longitude": "-1.36350090",
    "type": "metropolitan district",
    "timezone": "Europe/London",
    "CountryID": 232
  },
  {
    "id": 2472,
    "name": "Rutland",
    "iso2": "RUT",
    "native": "Rutland",
    "latitude": "52.64230360",
    "longitude": "-0.66326430",
    "type": "unitary authority",
    "timezone": "Europe/London",
    "CountryID": 232
  },
  {
    "id": 2493,
    "name": "Salford",
    "iso2": "SLF",
    "native": "Salford",
    "latitude": "53.48752350",
    "longitude": "-2.29012640",
    "type": "metropolitan district",
    "timezone": "Europe/London",
    "CountryID": 232
  },
  {
    "id": 2341,
    "name": "Sandwell",
    "iso2": "SAW",
    "native": "Sandwell",
    "latitude": "52.51484660",
    "longitude": "-2.01348890",
    "type": "metropolitan district",
    "timezone": "Europe/London",
    "CountryID": 232
  },
  {
    "id": 2335,
    "name": "Scotland",
    "iso2": "SCT",
    "native": "Scotland",
    "latitude": "56.78611120",
    "longitude": "-4.11405180",
    "type": "country",
    "timezone": "Europe/London",
    "CountryID": 232
  },
  {
    "id": 2346,
    "name": "Scottish Borders",
    "iso2": "SCB",
    "native": "Scottish Borders",
    "latitude": "55.58333300",
    "longitude": "-2.83333300",
    "type": "council area",
    "timezone": "Europe/London",
    "CountryID": 232
  },
  {
    "id": 2518,
    "name": "Sefton",
    "iso2": "SFT",
    "native": "Sefton",
    "latitude": "53.50344490",
    "longitude": "-2.97035900",
    "type": "metropolitan district",
    "timezone": "Europe/London",
    "CountryID": 232
  },
  {
    "id": 2295,
    "name": "Sheffield",
    "iso2": "SHF",
    "native": "Sheffield",
    "latitude": "53.38066260",
    "longitude": "-1.47022780",
    "type": "metropolitan district",
    "timezone": "Europe/London",
    "CountryID": 232
  },
  {
    "id": 2300,
    "name": "Shetland Islands",
    "iso2": "ZET",
    "native": "Shetland Islands",
    "latitude": "60.33333300",
    "longitude": "-1.33333300",
    "type": "council area",
    "timezone": "Europe/London",
    "CountryID": 232
  },
  {
    "id": 2407,
    "name": "Shropshire",
    "iso2": "SHR",
    "native": "Shropshire",
    "latitude": "52.65233930",
    "longitude": "-2.79586790",
    "type": "unitary authority",
    "timezone": "Europe/London",
    "CountryID": 232
  },
  {
    "id": 2427,
    "name": "Slough",
    "iso2": "SLG",
    "native": "Slough",
    "latitude": "51.51053840",
    "longitude": "-0.59504060",
    "type": "unitary authority",
    "timezone": "Europe/London",
    "CountryID": 232
  },
  {
    "id": 2469,
    "name": "Solihull",
    "iso2": "SOL",
    "native": "Solihull",
    "latitude": "52.41181100",
    "longitude": "-1.77761000",
    "type": "metropolitan district",
    "timezone": "Europe/London",
    "CountryID": 232
  },
  {
    "id": 2386,
    "name": "Somerset",
    "iso2": "SOM",
    "native": "Somerset",
    "latitude": "51.08333300",
    "longitude": "-3.00000000",
    "type": "two-tier county",
    "timezone": "Europe/London",
    "CountryID": 232
  },
  {
    "id": 2377,
    "name": "South Ayrshire",
    "iso2": "SAY",
    "native": "South Ayrshire",
    "latitude": "55.29981800",
    "longitude": "-4.64598840",
    "type": "council area",
    "timezone": "Europe/London",
    "CountryID": 232
  },
  {
    "id": 2400,
    "name": "South Gloucestershire",
    "iso2": "SGC",
    "native": "South Gloucestershire",
    "latitude": "51.54919160",
    "longitude": "-2.48095280",
    "type": "unitary authority",
    "timezone": "Europe/London",
    "CountryID": 232
  },
  {
    "id": 2362,
    "name": "South Lanarkshire",
    "iso2": "SLK",
    "native": "South Lanarkshire",
    "latitude": "55.58316340",
    "longitude": "-3.83322120",
    "type": "council area",
    "timezone": "Europe/London",
    "CountryID": 232
  },
  {
    "id": 2409,
    "name": "South Tyneside",
    "iso2": "STY",
    "native": "South Tyneside",
    "latitude": "54.96366930",
    "longitude": "-1.44186340",
    "type": "metropolitan district",
    "timezone": "Europe/London",
    "CountryID": 232
  },
  {
    "id": 2323,
    "name": "Southend-on-Sea",
    "iso2": "SOS",
    "native": "Southend-on-Sea",
    "latitude": "51.54592690",
    "longitude": "0.70771230",
    "type": "unitary authority",
    "timezone": "Europe/London",
    "CountryID": 232
  },
  {
    "id": 2432,
    "name": "Southwark",
    "iso2": "SWK",
    "native": "Southwark",
    "latitude": "51.46525450",
    "longitude": "-0.06901860",
    "type": "london borough",
    "timezone": "Europe/London",
    "CountryID": 232
  },
  {
    "id": 2290,
    "name": "St Helens",
    "iso2": "SHN",
    "native": "St Helens",
    "latitude": "53.45354710",
    "longitude": "-2.73432310",
    "type": "metropolitan district",
    "timezone": "Europe/London",
    "CountryID": 232
  },
  {
    "id": 2447,
    "name": "Staffordshire",
    "iso2": "STS",
    "native": "Staffordshire",
    "latitude": "52.82469420",
    "longitude": "-2.00745470",
    "type": "two-tier county",
    "timezone": "Europe/London",
    "CountryID": 232
  },
  {
    "id": 2488,
    "name": "Stirling",
    "iso2": "STG",
    "native": "Stirling",
    "latitude": "56.11652270",
    "longitude": "-3.93690290",
    "type": "council area",
    "timezone": "Europe/London",
    "CountryID": 232
  },
  {
    "id": 2394,
    "name": "Stockport",
    "iso2": "SKP",
    "native": "Stockport",
    "latitude": "53.41063160",
    "longitude": "-2.15753320",
    "type": "metropolitan district",
    "timezone": "Europe/London",
    "CountryID": 232
  },
  {
    "id": 2421,
    "name": "Stockton-on-Tees",
    "iso2": "STT",
    "native": "Stockton-on-Tees",
    "latitude": "54.56409400",
    "longitude": "-1.31291640",
    "type": "unitary authority",
    "timezone": "Europe/London",
    "CountryID": 232
  },
  {
    "id": 2506,
    "name": "Stoke-on-Trent",
    "iso2": "STE",
    "native": "Stoke-on-Trent",
    "latitude": "53.01620140",
    "longitude": "-2.18126070",
    "type": "unitary authority",
    "timezone": "Europe/London",
    "CountryID": 232
  },
  {
    "id": 2467,
    "name": "Suffolk",
    "iso2": "SFK",
    "native": "Suffolk",
    "latitude": "52.24100140",
    "longitude": "1.04657160",
    "type": "two-tier county",
    "timezone": "Europe/London",
    "CountryID": 232
  },
  {
    "id": 2372,
    "name": "Sunderland",
    "iso2": "SND",
    "native": "Sunderland",
    "latitude": "54.90585120",
    "longitude": "-1.38287270",
    "type": "metropolitan district",
    "timezone": "Europe/London",
    "CountryID": 232
  },
  {
    "id": 2526,
    "name": "Surrey",
    "iso2": "SRY",
    "native": "Surrey",
    "latitude": "51.27153160",
    "longitude": "-0.34145240",
    "type": "two-tier county",
    "timezone": "Europe/London",
    "CountryID": 232
  },
  {
    "id": 2313,
    "name": "Sutton",
    "iso2": "STN",
    "native": "Suton",
    "latitude": "51.35737620",
    "longitude": "-0.17527960",
    "type": "london borough",
    "timezone": "Europe/London",
    "CountryID": 232
  },
  {
    "id": 2433,
    "name": "Swansea",
    "iso2": "SWA",
    "native": "Swansea",
    "latitude": "51.62144000",
    "longitude": "-3.94364600",
    "type": "unitary authority",
    "timezone": "Europe/London",
    "CountryID": 232
  },
  {
    "id": 2422,
    "name": "Swindon",
    "iso2": "SWD",
    "native": "Swindon",
    "latitude": "51.55577390",
    "longitude": "-1.77971760",
    "type": "unitary authority",
    "timezone": "Europe/London",
    "CountryID": 232
  },
  {
    "id": 2367,
    "name": "Tameside",
    "iso2": "TAM",
    "native": "Tameside",
    "latitude": "53.48058280",
    "longitude": "-2.08098910",
    "type": "metropolitan district",
    "timezone": "Europe/London",
    "CountryID": 232
  },
  {
    "id": 2310,
    "name": "Telford and Wrekin",
    "iso2": "TFW",
    "native": "Telford and Wrekin",
    "latitude": "52.72144520",
    "longitude": "-2.50086240",
    "type": "unitary authority",
    "timezone": "Europe/London",
    "CountryID": 232
  },
  {
    "id": 2468,
    "name": "Thurrock",
    "iso2": "THR",
    "native": "Thurrock",
    "latitude": "51.50801690",
    "longitude": "0.39628170",
    "type": "unitary authority",
    "timezone": "Europe/London",
    "CountryID": 232
  },
  {
    "id": 2478,
    "name": "Torbay",
    "iso2": "TOB",
    "native": "Torbay",
    "latitude": "50.43923290",
    "longitude": "-3.53698990",
    "type": "unitary authority",
    "timezone": "Europe/London",
    "CountryID": 232
  },
  {
    "id": 2496,
    "name": "Torfaen",
    "iso2": "TOF",
    "native": "Torfaen",
    "latitude": "51.70022530",
    "longitude": "-3.04460150",
    "type": "unitary authority",
    "timezone": "Europe/London",
    "CountryID": 232
  },
  {
    "id": 2390,
    "name": "Tower Hamlets",
    "iso2": "TWH",
    "native": "Tower Hamlets",
    "latitude": "51.12886330",
    "longitude": "1.29866860",
    "type": "london borough",
    "timezone": "Europe/London",
    "CountryID": 232
  },
  {
    "id": 2293,
    "name": "Trafford",
    "iso2": "TRF",
    "native": "Trafford",
    "latitude": "53.41893600",
    "longitude": "-2.35929720",
    "type": "metropolitan district",
    "timezone": "Europe/London",
    "CountryID": 232
  },
  {
    "id": 2299,
    "name": "Vale of Glamorgan",
    "iso2": "VGL",
    "native": "Vale of Glamorgan",
    "latitude": "51.44706460",
    "longitude": "-3.39888310",
    "type": "unitary authority",
    "timezone": "Europe/London",
    "CountryID": 232
  },
  {
    "id": 2465,
    "name": "Wakefield",
    "iso2": "WKF",
    "native": "Wakefield",
    "latitude": "53.68295410",
    "longitude": "-1.49672860",
    "type": "metropolitan district",
    "timezone": "Europe/London",
    "CountryID": 232
  },
  {
    "id": 2338,
    "name": "Wales",
    "iso2": "WLS",
    "native": "Wales",
    "latitude": "52.29281160",
    "longitude": "-3.73893000",
    "type": "country",
    "timezone": "Europe/London",
    "CountryID": 232
  },
  {
    "id": 2292,
    "name": "Walsall",
    "iso2": "WLL",
    "native": "Walsall",
    "latitude": "52.58621400",
    "longitude": "-1.98291900",
    "type": "metropolitan district",
    "timezone": "Europe/London",
    "CountryID": 232
  },
  {
    "id": 2326,
    "name": "Waltham Forest",
    "iso2": "WFT",
    "native": "Waltham Forest",
    "latitude": "51.59826330",
    "longitude": "-0.01773880",
    "type": "london borough",
    "timezone": "Europe/London",
    "CountryID": 232
  },
  {
    "id": 2434,
    "name": "Wandsworth",
    "iso2": "WND",
    "native": "Wandsworth",
    "latitude": "51.45682740",
    "longitude": "-0.18966380",
    "type": "london borough",
    "timezone": "Europe/London",
    "CountryID": 232
  },
  {
    "id": 2420,
    "name": "Warrington",
    "iso2": "WRT",
    "native": "Warrington",
    "latitude": "53.38994970",
    "longitude": "-2.59431780",
    "type": "unitary authority",
    "timezone": "Europe/London",
    "CountryID": 232
  },
  {
    "id": 2505,
    "name": "Warwickshire",
    "iso2": "WAR",
    "native": "Warwickshire",
    "latitude": "52.32130640",
    "longitude": "-1.55369060",
    "type": "two-tier county",
    "timezone": "Europe/London",
    "CountryID": 232
  },
  {
    "id": 2471,
    "name": "West Berkshire",
    "iso2": "WBK",
    "native": "West Berkshire",
    "latitude": "51.44631340",
    "longitude": "-1.27588200",
    "type": "unitary authority",
    "timezone": "Europe/London",
    "CountryID": 232
  },
  {
    "id": 2440,
    "name": "West Dunbartonshire",
    "iso2": "WDU",
    "native": "West Dunbartonshire",
    "latitude": "55.96666700",
    "longitude": "-4.53333300",
    "type": "council area",
    "timezone": "Europe/London",
    "CountryID": 232
  },
  {
    "id": 2354,
    "name": "West Lothian",
    "iso2": "WLN",
    "native": "West Lothian",
    "latitude": "55.91666700",
    "longitude": "-3.50000000",
    "type": "council area",
    "timezone": "Europe/London",
    "CountryID": 232
  },
  {
    "id": 5462,
    "name": "West Northamptonshire",
    "iso2": "WNH",
    "native": "West Northamptonshire",
    "latitude": "52.22689770",
    "longitude": "-1.34831910",
    "type": "unitary authority",
    "timezone": "Europe/London",
    "CountryID": 232
  },
  {
    "id": 2296,
    "name": "West Sussex",
    "iso2": "WSX",
    "native": "West Sussex",
    "latitude": "50.94458450",
    "longitude": "-0.52784770",
    "type": "two-tier county",
    "timezone": "Europe/London",
    "CountryID": 232
  },
  {
    "id": 2357,
    "name": "Westminster",
    "iso2": "WSM",
    "native": "Westminster",
    "latitude": "51.49732060",
    "longitude": "-0.13714900",
    "type": "london borough",
    "timezone": "Europe/London",
    "CountryID": 232
  },
  {
    "id": 2320,
    "name": "Wigan",
    "iso2": "WGN",
    "native": "Wigan",
    "latitude": "53.54571880",
    "longitude": "-2.62646240",
    "type": "metropolitan district",
    "timezone": "Europe/London",
    "CountryID": 232
  },
  {
    "id": 2391,
    "name": "Wiltshire",
    "iso2": "WIL",
    "native": "Wiltshire",
    "latitude": "51.32416200",
    "longitude": "-1.90324870",
    "type": "unitary authority",
    "timezone": "Europe/London",
    "CountryID": 232
  },
  {
    "id": 2482,
    "name": "Windsor and Maidenhead",
    "iso2": "WNM",
    "native": "Windsor and Maidenhead",
    "latitude": "51.48034120",
    "longitude": "-0.67695050",
    "type": "unitary authority",
    "timezone": "Europe/London",
    "CountryID": 232
  },
  {
    "id": 2408,
    "name": "Wirral",
    "iso2": "WRL",
    "native": "Wirral",
    "latitude": "53.34097140",
    "longitude": "-3.05009160",
    "type": "metropolitan district",
    "timezone": "Europe/London",
    "CountryID": 232
  },
  {
    "id": 2419,
    "name": "Wokingham",
    "iso2": "WOK",
    "native": "Wokingham",
    "latitude": "51.41045700",
    "longitude": "-0.83386100",
    "type": "unitary authority",
    "timezone": "Europe/London",
    "CountryID": 232
  },
  {
    "id": 2489,
    "name": "Wolverhampton",
    "iso2": "WLV",
    "native": "Wolverhampton",
    "latitude": "52.58476510",
    "longitude": "-2.12756700",
    "type": "metropolitan district",
    "timezone": "Europe/London",
    "CountryID": 232
  },
  {
    "id": 2510,
    "name": "Worcestershire",
    "iso2": "WOR",
    "native": "Worcestershire",
    "latitude": "52.21094950",
    "longitude": "-2.15695550",
    "type": "two-tier county",
    "timezone": "Europe/London",
    "CountryID": 232
  },
  {
    "id": 2436,
    "name": "Wrexham",
    "iso2": "WRX",
    "native": "Wrexham",
    "latitude": "53.04650840",
    "longitude": "-2.99378690",
    "type": "unitary authority",
    "timezone": "Europe/London",
    "CountryID": 232
  },
  {
    "id": 2426,
    "name": "York",
    "iso2": "YOR",
    "native": "York",
    "latitude": "53.95996510",
    "longitude": "-1.08729790",
    "type": "unitary authority",
    "timezone": "Europe/London",
    "CountryID": 232
  }
]